[
  {
    "id": 5575920066,
    "name": "广州视寰电子科技有限公司",
    "regStatus": "存续",
    "province": "广东省",
    "city": "广州市",
    "category": "信息传输、软件和信息技术服务业",
    "amount": "1000万元人民币",
    "percent": "100%",
    "legalPersonName": "王琪峰",
    "establishTime": 1655913600000,
    "regCapital": "1000万人民币",
    "industry": "信息传输、软件和信息技术服务业"
  },
  {
    "id": 6456601505,
    "name": "深圳视睿电子科技有限公司",
    "regStatus": "存续",
    "province": "广东省",
    "city": "深圳市",
    "category": "科学研究和技术服务业",
    "amount": "1000万元人民币",
    "percent": "100%",
    "legalPersonName": "张凌",
    "establishTime": 1693411200000,
    "regCapital": "1000万人民币",
    "industry": "科学研究和技术服务业"
  },
  {
    "id": 6012019942,
    "name": "厦门视睿电子科技有限公司",
    "regStatus": "存续",
    "province": "福建省",
    "city": "厦门市",
    "category": "制造业",
    "amount": "1000万元人民币",
    "percent": "100%",
    "legalPersonName": "张凌",
    "establishTime": 1680105600000,
    "regCapital": "1000万人民币",
    "industry": "制造业"
  },
  {
    "id": 5944243032,
    "name": "西安希沃电子科技有限公司",
    "regStatus": "存续",
    "province": "陕西省",
    "city": "西安市",
    "category": "科学研究和技术服务业",
    "amount": "900万元人民币",
    "percent": "60%",
    "legalPersonName": "孙毅拯",
    "establishTime": 1677081600000,
    "regCapital": "1500万人民币",
    "industry": "科学研究和技术服务业"
  },
  {
    "id": 5898268763,
    "name": "山东视睿创新智能科技有限公司",
    "regStatus": "存续",
    "province": "山东省",
    "city": "济南市",
    "category": "信息传输、软件和信息技术服务业",
    "amount": "756万元人民币",
    "percent": "60%",
    "legalPersonName": "马东",
    "establishTime": 1675353600000,
    "regCapital": "1260万人民币",
    "industry": "信息传输、软件和信息技术服务业"
  },
  {
    "id": 7874123774,
    "name": "浙江视昂电子科技有限公司",
    "regStatus": "存续",
    "province": "浙江省",
    "city": "杭州市",
    "category": "科学研究和技术服务业",
    "amount": "750万元人民币",
    "percent": "60%",
    "legalPersonName": "汪涛",
    "establishTime": 1764691200000,
    "regCapital": "1250万人民币",
    "industry": "科学研究和技术服务业"
  },
  {
    "id": 6222791445,
    "name": "海南视睿电子科技有限公司",
    "regStatus": "存续",
    "province": "海南省",
    "city": "省直辖县级行政区划",
    "category": "信息传输、软件和信息技术服务业",
    "amount": "750万元人民币",
    "percent": "60%",
    "legalPersonName": "刘华豪",
    "establishTime": 1686067200000,
    "regCapital": "1250万人民币",
    "industry": "信息传输、软件和信息技术服务业"
  },
  {
    "id": 5902174537,
    "name": "江苏视睿浩源电子科技有限公司",
    "regStatus": "存续",
    "province": "江苏省",
    "city": "南京市",
    "category": "信息传输、软件和信息技术服务业",
    "amount": "750万元人民币",
    "percent": "60%",
    "legalPersonName": "王磊",
    "establishTime": 1673971200000,
    "regCapital": "1250万人民币",
    "industry": "信息传输、软件和信息技术服务业"
  },
  {
    "id": 6843451769,
    "name": "湖南源沃电子科技有限公司",
    "regStatus": "存续",
    "province": "湖南省",
    "city": "长沙市",
    "category": "科学研究和技术服务业",
    "amount": "600万元人民币",
    "percent": "60%",
    "legalPersonName": "苏刚",
    "establishTime": 1710432000000,
    "regCapital": "1000万人民币",
    "industry": "科学研究和技术服务业"
  },
  {
    "id": 6665700036,
    "name": "四川视睿启创电子科技有限公司",
    "regStatus": "存续",
    "province": "四川省",
    "city": "成都市",
    "category": "科学研究和技术服务业",
    "amount": "600万元人民币",
    "percent": "60%",
    "legalPersonName": "胡鹄飞",
    "establishTime": 1701273600000,
    "regCapital": "1000万人民币",
    "industry": "科学研究和技术服务业"
  },
  {
    "id": 6226829247,
    "name": "福建视晞电子科技有限公司",
    "regStatus": "存续",
    "province": "福建省",
    "city": "厦门市",
    "category": "科学研究和技术服务业",
    "amount": "600万元人民币",
    "percent": "60%",
    "legalPersonName": "陈惠聪",
    "establishTime": 1686153600000,
    "regCapital": "1000万人民币",
    "industry": "科学研究和技术服务业"
  },
  {
    "id": 6177972041,
    "name": "江西视猷电子科技有限公司",
    "regStatus": "存续",
    "province": "江西省",
    "city": "南昌市",
    "category": "信息传输、软件和信息技术服务业",
    "amount": "600万元人民币",
    "percent": "60%",
    "legalPersonName": "袁宝华",
    "establishTime": 1684252800000,
    "regCapital": "1000万人民币",
    "industry": "信息传输、软件和信息技术服务业"
  },
  {
    "id": 6139798348,
    "name": "希沃（辽宁）电子科技有限公司",
    "regStatus": "存续",
    "province": "辽宁省",
    "city": "沈阳市",
    "category": "制造业",
    "amount": "600万元人民币",
    "percent": "60%",
    "legalPersonName": "孙成昌",
    "establishTime": 1683561600000,
    "regCapital": "1000万人民币",
    "industry": "制造业"
  },
  {
    "id": 5946096003,
    "name": "北京视睿源创科技有限公司",
    "regStatus": "存续",
    "province": "北京市",
    "city": "通州区",
    "category": "科学研究和技术服务业",
    "amount": "600万元人民币",
    "percent": "60%",
    "legalPersonName": "杨威",
    "establishTime": 1676563200000,
    "regCapital": "1000万人民币",
    "industry": "科学研究和技术服务业"
  },
  {
    "id": 5785962268,
    "name": "郑州视睿电子科技有限公司",
    "regStatus": "存续",
    "province": "河南省",
    "city": "郑州市",
    "category": "信息传输、软件和信息技术服务业",
    "amount": "600万元人民币",
    "percent": "60%",
    "legalPersonName": "吴超",
    "establishTime": 1667404800000,
    "regCapital": "1000万人民币",
    "industry": "信息传输、软件和信息技术服务业"
  },
  {
    "id": 5751833589,
    "name": "武汉视睿电子科技有限公司",
    "regStatus": "存续",
    "province": "湖北省",
    "city": "武汉市",
    "category": "信息传输、软件和信息技术服务业",
    "amount": "600万元人民币",
    "percent": "60%",
    "legalPersonName": "程煜",
    "establishTime": 1665936000000,
    "regCapital": "1000万人民币",
    "industry": "信息传输、软件和信息技术服务业"
  },
  {
    "id": 5346975873,
    "name": "合肥源沃长合电子科技有限公司",
    "regStatus": "存续",
    "province": "安徽省",
    "city": "合肥市",
    "category": "科学研究和技术服务业",
    "amount": "600万元人民币",
    "percent": "60%",
    "legalPersonName": "吴铮",
    "establishTime": 1643126400000,
    "regCapital": "1000万人民币",
    "industry": "科学研究和技术服务业"
  },
  {
    "id": 5748539889,
    "name": "广州希倍思智能科技有限公司",
    "regStatus": "存续",
    "province": "广东省",
    "city": "广州市",
    "category": "制造业",
    "amount": "523万元人民币",
    "percent": "52.3%",
    "legalPersonName": "邱澈",
    "establishTime": 1665676800000,
    "regCapital": "1000万人民币",
    "industry": "制造业"
  },
  {
    "id": 6659245506,
    "name": "贵州视睿电子科技有限公司",
    "regStatus": "存续",
    "province": "贵州省",
    "city": "遵义市",
    "category": "信息传输、软件和信息技术服务业",
    "amount": "450万元人民币",
    "percent": "60%",
    "legalPersonName": "钱俊桦",
    "establishTime": 1701014400000,
    "regCapital": "750万人民币",
    "industry": "信息传输、软件和信息技术服务业"
  },
  {
    "id": 6206544981,
    "name": "云南视睿滇合信息科技有限公司",
    "regStatus": "存续",
    "province": "云南省",
    "city": "昆明市",
    "category": "信息传输、软件和信息技术服务业",
    "amount": "450万元人民币",
    "percent": "60%",
    "legalPersonName": "韩泽治",
    "establishTime": 1685462400000,
    "regCapital": "750万人民币",
    "industry": "信息传输、软件和信息技术服务业"
  },
  {
    "id": 6171355551,
    "name": "上海视熙智能科技有限公司",
    "regStatus": "存续",
    "province": "上海市",
    "city": "徐汇区",
    "category": "信息传输、软件和信息技术服务业",
    "amount": "450万元人民币",
    "percent": "60%",
    "legalPersonName": "刘畅",
    "establishTime": 1684252800000,
    "regCapital": "750万人民币",
    "industry": "信息传输、软件和信息技术服务业"
  },
  {
    "id": 5750545192,
    "name": "重庆视睿电子科技有限公司",
    "regStatus": "存续",
    "province": "重庆市",
    "city": "渝北区",
    "category": "科学研究和技术服务业",
    "amount": "450万元人民币",
    "percent": "60%",
    "legalPersonName": "袁杰",
    "establishTime": 1665676800000,
    "regCapital": "750万人民币",
    "industry": "科学研究和技术服务业"
  },
  {
    "id": 6341472128,
    "name": "山西视昂源启科技有限公司",
    "regStatus": "存续",
    "province": "山西省",
    "city": "太原市",
    "category": "科学研究和技术服务业",
    "amount": "367.5万元人民币",
    "percent": "49%",
    "legalPersonName": "武文路",
    "establishTime": 1690387200000,
    "regCapital": "750万人民币",
    "industry": "科学研究和技术服务业"
  },
  {
    "id": 6237814216,
    "name": "内蒙古视晟电子科技有限公司",
    "regStatus": "存续",
    "province": "内蒙古自治区",
    "city": "呼和浩特市",
    "category": "科学研究和技术服务业",
    "amount": "180万元人民币",
    "percent": "60%",
    "legalPersonName": "王光德",
    "establishTime": 1686067200000,
    "regCapital": "300万人民币",
    "industry": "科学研究和技术服务业"
  },
  {
    "id": 5312822746,
    "name": "河北视翊电子科技有限公司",
    "regStatus": "存续",
    "province": "河北省",
    "city": "邢台市",
    "category": "科学研究和技术服务业",
    "amount": "180万元人民币",
    "percent": "60%",
    "legalPersonName": "刁旭",
    "establishTime": 1640707200000,
    "regCapital": "300万人民币",
    "industry": "科学研究和技术服务业"
  },
  {
    "id": 6849087442,
    "name": "广州视睿沃途科技有限公司",
    "regStatus": "存续",
    "province": "广东省",
    "city": "广州市",
    "category": "科学研究和技术服务业",
    "amount": "140万元人民币",
    "percent": "70%",
    "legalPersonName": "张凌",
    "establishTime": 1710777600000,
    "regCapital": "200万人民币",
    "industry": "科学研究和技术服务业"
  },
  {
    "id": 5048650846,
    "name": "广东师大智能科技有限公司",
    "regStatus": "存续",
    "province": "广东省",
    "city": "广州市",
    "category": "信息传输、软件和信息技术服务业",
    "amount": "25万元人民币",
    "percent": "4.7619%",
    "legalPersonName": "蒋文忠",
    "establishTime": 1626710400000,
    "regCapital": "525万人民币",
    "industry": "信息传输、软件和信息技术服务业"
  },
  {
    "id": 2358011907,
    "name": "广州华蒙星体育发展有限公司",
    "regStatus": "存续",
    "province": "广东省",
    "city": "广州市",
    "category": "文化、体育和娱乐业",
    "amount": "5.4348万元人民币",
    "percent": "5%",
    "legalPersonName": "温大治",
    "establishTime": 1458662400000,
    "regCapital": "108.6956万人民币",
    "industry": "文化、体育和娱乐业"
  },
  {
    "id": 5344641243,
    "name": "山西视昂源硕科技有限公司",
    "regStatus": "注销",
    "province": "山西省",
    "city": "太原市",
    "category": "科学研究和技术服务业",
    "amount": "700万元人民币",
    "percent": "70%",
    "legalPersonName": "邓毅刚",
    "establishTime": 1642953600000,
    "regCapital": "1000万人民币",
    "industry": "科学研究和技术服务业"
  }
]